<?xml version="1.0" encoding="utf-8" ?>
<Countys>
  <County ID="0" State="1" Name="Bocas del Toro"  />
  <County ID="1" State="1" Name="Changuinola"  />
  <County ID="2" State="1" Name="Chiriquí Grande"  />

  <County ID="3" State="2" Name="Aguadulce"  />
  <County ID="4" State="2" Name="Antón"  />
  <County ID="5" State="2" Name="La Pintada"  />
  <County ID="6" State="2" Name="Natá"  />
  <County ID="7" State="2" Name="Olá"  />
  <County ID="8" State="2" Name="Penonomé"  />

  <County ID="9" State="3" Name="Colón"  />
  <County ID="10" State="3" Name="Chagres"  />
  <County ID="11" State="3" Name="Donoso"  />
  <County ID="12" State="3" Name="Portobelo"  />
  <County ID="13" State="3" Name="Santa Isabel"  />

  <County ID="14" State="4" Name="Alanje"  />
  <County ID="15" State="4" Name="Barú"  />
  <County ID="16" State="4" Name="Boquerón"  />
  <County ID="17" State="4" Name="Boquete"  />
  <County ID="18" State="4" Name="Bugaba"  />
  <County ID="19" State="4" Name="David"  />
  <County ID="20" State="4" Name="Dolega"  />
  <County ID="21" State="4" Name="Gualaca"  />
  <County ID="22" State="4" Name="Remedios"  />
  <County ID="23" State="4" Name="Renacimiento"  />
  <County ID="24" State="4" Name="San Félix"  />
  <County ID="25" State="4" Name="San Lorenzo"  />
  <County ID="26" State="4" Name="Tolé"  />

  <County ID="27" State="5" Name="Chepigana"  />
  <County ID="28" State="5" Name="Pinogana"  />

  <County ID="29" State="6" Name="Cémaco"  />
  <County ID="30" State="6" Name="Sambú"  />

  <County ID="31" State="7" Name="Guna Yala"  />

  <County ID="32" State="8" Name="Chitré"  />
  <County ID="33" State="8" Name="Las Minas"  />
  <County ID="34" State="8" Name="Los Pozos"  />
  <County ID="35" State="8" Name="Ocú"  />
  <County ID="36" State="8" Name="Parita"  />
  <County ID="37" State="8" Name="Pesé"  />
  <County ID="38" State="8" Name="Santa María"  />

  <County ID="39" State="9" Name="Guararé"  />
  <County ID="40" State="9" Name="Las Tablas"  />
  <County ID="41" State="9" Name="Los Santos"  />
  <County ID="42" State="9" Name="Macaracas"  />
  <County ID="43" State="9" Name="Pedasí"  />
  <County ID="44" State="9" Name="Pocrí"  />
  <County ID="45" State="9" Name="Tonosí"  />

  <County ID="46" State="10" Name="Besikó"  />
  <County ID="47" State="10" Name="Kankintú"  />
  <County ID="48" State="10" Name="Kusapín"  />
  <County ID="49" State="10" Name="Mironó"  />
  <County ID="50" State="10" Name="Nole Düima"  />
  <County ID="51" State="10" Name="Müna"  />
  <County ID="52" State="10" Name="Ñürüm"  />


  <County ID="53" State="11" Name="Balboa"  />
  <County ID="54" State="11" Name="Chepo"  />
  <County ID="55" State="11" Name="Chimán"  />
  <County ID="56" State="11" Name="Panamá"  />
  <County ID="57" State="11" Name="San Miguelito"  />
  <County ID="58" State="11" Name="Taboga"  />

  <County ID="59" State="12" Name="Arraijan"  />
  <County ID="60" State="12" Name="Capira"  />
  <County ID="61" State="12" Name="Chame"  />
  <County ID="62" State="12" Name="La Chorrera"  />
  <County ID="63" State="12" Name="San Carlos"  />

  <County ID="64" State="13" Name="Atalaya"  />
  <County ID="65" State="13" Name="Calobre"  />
  <County ID="66" State="13" Name="Cañazas"  />
  <County ID="67" State="13" Name="La Mesa"  />
  <County ID="68" State="13" Name="Las Palmas"  />
  <County ID="69" State="13" Name="Mariato"  />
  <County ID="70" State="13" Name="Montijo"  />
  <County ID="71" State="13" Name="Río de Jesús"  />
  <County ID="72" State="13" Name="San Francisco"  />
  <County ID="73" State="13" Name="Santa Fe"  />
  <County ID="74" State="13" Name="Santiago"  />
  <County ID="75" State="13" Name="Soná"  />
</Countys>
